setup.py
pyshark_parser/__init__.py
pyshark_parser/layer_util.py
pyshark_parser/packet_util.py
pyshark_parser/pcap_util.py
pyshark_parser.egg-info/PKG-INFO
pyshark_parser.egg-info/SOURCES.txt
pyshark_parser.egg-info/dependency_links.txt
pyshark_parser.egg-info/not-zip-safe
pyshark_parser.egg-info/requires.txt
pyshark_parser.egg-info/top_level.txt