Metadata-Version: 1.0
Name: pyshark_parser
Version: 0.1
Summary: A library for parsing pyshark pcap objects
Home-page: http://github.com/jlents/pyshark_parser
Author: Joshua Lents
Author-email: joshua.lents@gmail.com
License: MIT
Platform: UNKNOWN
